mass_analytics/__init__.py
mass_analytics/data_frame_util.py
mass_analytics/data_overview.py
mass_analytics/date.py
mass_analytics/keywords.py
mass_analytics/plotting.py
mass_analytics/reader.py
mass_analytics-1.3.4.dist-info/METADATA
mass_analytics-1.3.4.dist-info/WHEEL
mass_analytics-1.3.4.dist-info/licenses/LICENSE.txt
mass_analytics-1.3.4.dist-info/RECORD
