Metadata-Version: 2.1
Name: mass_analytics
Version: 1.3.4
Summary: Streamline data preprocessing and enhance analysis with our Powerful Data Preparation Package.
Author-email: Selim <alouiniselim@gmail.com>
License-File: LICENSE.txt
Classifier: License :: OSI Approved :: MIT License
Classifier: Operating System :: OS Independent
Classifier: Programming Language :: Python :: 3
Requires-Python: >=3.7
Requires-Dist: fuzzywuzzy
Requires-Dist: numpy==1.25.1
Requires-Dist: openpyxl
Requires-Dist: pandas==2.0.3
Requires-Dist: plotly==5.15.0
Requires-Dist: python-levenshtein
Requires-Dist: streamlit==1.24.1
Requires-Dist: tqdm
